bethic/EDA.py
bethic/ML.py
bethic/PCA.py
bethic/__init__.py
bethic/dashboard.py
bethic/mongo_operations.py
bethic/pca_lib.py
bethic/python_postprocess.py
bethic/python_preprocess.py
bethic/utils.py
bethic_funcs-0.0.1.dist-info/LICENSE
bethic_funcs-0.0.1.dist-info/METADATA
bethic_funcs-0.0.1.dist-info/WHEEL
bethic_funcs-0.0.1.dist-info/top_level.txt
bethic_funcs-0.0.1.dist-info/RECORD
